discard/__init__.py
discard/__main__.py
discard/cli.py
discard/discard.py
discard/test_discard.py
discord_discard-0.1.4.dist-info/LICENSE
discord_discard-0.1.4.dist-info/METADATA
discord_discard-0.1.4.dist-info/WHEEL
discord_discard-0.1.4.dist-info/top_level.txt
discord_discard-0.1.4.dist-info/RECORD
