Metadata-Version: 2.1
Name: discord-discard
Version: 0.1.4
Summary: Tool for medium-scale Discord server archival operations
Home-page: https://github.com/Sanqui/discard
Author: Sanqui
Author-email: me@sanqui.net
License: UNKNOWN
Platform: UNKNOWN
Classifier: Programming Language :: Python :: 3
Classifier: Operating System :: OS Independent
Requires-Python: >=3.6
Requires-Dist: discord.py (==1.6.0)
Requires-Dist: click (==7.1.2)
